{
  "id": "tid-ett-vaccinationspaket-för-äldre-värt-112-miljoner",
  "name": "Ett vaccinationspaket för äldre värt 112 miljoner kronor, med fokus på ikappvaccinering mot pneumoko",
  "description": "Ett vaccinationspaket för äldre värt 112 miljoner kronor, med fokus på ikappvaccinering mot pneumokocker.",
  "party": "Tidöpartierna",
  "status": "Pågående",
  "date": "2026-04-13",
  "sources": [
    {
      "value": "https://www.svt.se/nyheter/inrikes/sa-paverkas-du-av-regeringens-varbudget",
      "archive": ""
    }
  ],
  "tags": [],
  "updates": []
}
